term2web/__init__.py
term2web/term2web.py
term2web-0.0.4.dist-info/LICENSE
term2web-0.0.4.dist-info/METADATA
term2web-0.0.4.dist-info/WHEEL
term2web-0.0.4.dist-info/top_level.txt
term2web-0.0.4.dist-info/RECORD
