Metadata-Version: 2.1
Name: term2web
Version: 0.0.4
Summary: Toolkit which overloads 'print(…)' and 'input()' to redirect them to a web page.
Home-page: https://github.com/epeios-q37/term2web-python
Author: Claude SIMON
License: UNKNOWN
Keywords: cli,web,term,terminal,text,Atlas toolkit,atlastk
Platform: UNKNOWN
Classifier: Development Status :: 5 - Production/Stable
Classifier: Environment :: Console
Classifier: Environment :: Web Environment
Classifier: Intended Audience :: Developers
Classifier: Intended Audience :: Education
Classifier: License :: OSI Approved :: MIT License 
Classifier: Operating System :: OS Independent
Classifier: Programming Language :: Python :: 3
Classifier: Topic :: Education
Requires-Dist: atlastk
